skradar/__init__.py
skradar/misc.py
skradar/process.py
skradar/radar_scene.py
skradar/sim.py
skradar/version.py
skradar/detection/__init__.py
skradar/detection/cfar.py
scikit_radar-0.0.2.dist-info/LICENSE
scikit_radar-0.0.2.dist-info/METADATA
scikit_radar-0.0.2.dist-info/WHEEL
scikit_radar-0.0.2.dist-info/top_level.txt
scikit_radar-0.0.2.dist-info/RECORD
